dramatts/__init__.py
dramatts/core.py
dramatts/dramatts_gui.py
dramatts/gui.py
dramatts/voices.py
dramatts-0.2.1.dist-info/COPYING
dramatts-0.2.1.dist-info/LICENSE
dramatts-0.2.1.dist-info/METADATA
dramatts-0.2.1.dist-info/WHEEL
dramatts-0.2.1.dist-info/top_level.txt
dramatts-0.2.1.dist-info/RECORD
