Metadata-Version: 2.1
Name: dramatts
Version: 0.2.1
Summary: Screen play / drama text to multi-voice audio play converter
Home-page: https://dramatts.readthedocs.io/en/latest/
Author: Thies Hecker
Author-email: thies.hecker@gmx.de
License: GPL3
Project-URL: Documentation, https://dramatts.readthedocs.io/en/latest/
Project-URL: Source Code, https://gitlab.com/thecker/dramatts/
Keywords: TTS play text-to-speech festival audio book
Platform: UNKNOWN
Classifier: License :: OSI Approved :: GNU General Public License v3 (GPLv3)
Requires-Python: >=3
Requires-Dist: PyQt5
Requires-Dist: setuptools-scm
Requires-Dist: jinja2
Requires-Dist: pytest
